{
    "status": 1,
    "msg": "Success",
    "data": [
        {
            "id": 1,
            "parent_complaint_id": 0,
            "parent_complaint_code": "",
            "complaint_date_int": 240229,
            "complaint_serial": 1,
            "complaint_code": "GW/240229/00001",
            "cust_id": 1,
            "cust_code": "CUST0000000001",
            "cust_name": "Debashis Giri & Com.",
            "cust_phone": "9999000099",
            "cust_email": "debashis.giri@webspiders.com",
            "rep_id": 1,
            "rep_code": "REP000001",
            "contact_name": "Deb G",
            "contact_phone": "9990009901",
            "contact_alt_phone": "9990009900",
            "contact_email": "debashis.giri@webspiders.com",
            "equip_id": 1,
            "equip_serial_no": "120E96ACFKT",
            "equip_model": "CAT-5931533",
            "equip_category_code": "O",
            "equip_category_name": "OEM",
            "equip_status_code": "R",
            "equip_status_name": "Running",
            "equip_smu": null,
            "equip_smu_date": null,
            "fault_code": "1",
            "fault_name": "fault name",
            "complaint_description": "complaint description",
            "equip_country_code": "IN",
            "equip_country_name": "India",
            "equip_state_code": "IN-WB",
            "equip_state_name": "West Bengal",
            "equip_district_code": "",
            "equip_district_name": "",
            "equip_pincode": "",
            "equip_address": "",
            "call_type_code": null,
            "call_type_name": null,
            "visit_type_code": null,
            "visit_type_name": null,
            "call_priority_code": null,
            "call_priority_name": null,
            "promis_hours": null,
            "psm_id": null,
            "psm_code": null,
            "psm_name": null,
            "psm_assigned_date": null,
            "psm_assigned_by": null,
            "cse_id": null,
            "cse_code": null,
            "cse_name": null,
            "cse_assigned_date": null,
            "cse_assigned_by": null,
            "cse_accept_status": null,
            "cse_start_time": null,
            "cse_completion_time": null,
            "cse_remarks": null,
            "cse_remarks_images": [],
            "customer_feedback": null,
            "customer_feedback_rating": null,
            "customer_feedback_date": null,
            "status": 1,
            "status_code": "R",
            "status_name": "Registered",
            "child_status": 1,
            "child_status_code": "",
            "child_status_name": "",
            "reopened": false,
            "created_by": 1,
            "created_date": "2024-02-28T16:59:11.997Z",
            "last_modified_by": null,
            "last_modified_date": null
        }
    ]
}